nimue/__init__.py
nimue/_config.py
nimue/_execution_tester.py
nimue/_execution_tracer.py
nimue/_file_storage_manager.py
nimue/_module_loader.py
nimue/_tracer.py
nimue/skeleton.py
nimue/version.ini
nimue/utils/__init__.py
nimue/utils/base.py
nimue/utils/logging.py
nimue_plugins/comparing.py
nimue_plugins/comparing/console/content_compare.py
nimue_plugins/comparing/exitcode/value_compare.py
nimue_plugins/comparing/files/__init__.py
nimue_plugins/comparing/files/csv_compare.py
nimue_plugins/comparing/files/default_compare.py
nimue_plugins/comparing/files/hdf5_compare.py
nimue_plugins/comparing/files/json_compare.py
nimue_plugins/comparing/files/yaml_compare.py
nimue_plugins/comparing/metadata/semver_compare.py
nimue_rt-0.4.0.dist-info/LICENSE.txt
nimue_rt-0.4.0.dist-info/METADATA
nimue_rt-0.4.0.dist-info/WHEEL
nimue_rt-0.4.0.dist-info/entry_points.txt
nimue_rt-0.4.0.dist-info/top_level.txt
nimue_rt-0.4.0.dist-info/RECORD
