Metadata-Version: 2.1
Name: nimue-rt
Version: 0.4.0
Summary: A flexible and extensible regression testing framework for Python projects, designed to simplify tracking and comparing execution outcomes
Home-page: https://github.com/cogniteva/nimue-rt
Author: Cogniteva SAS
Author-email: opensource@cogniteva.fr
License: MIT
Project-URL: Source, https://github.com/cogniteva/nimue-rt/
Project-URL: Documentation, https://cogniteva.dev/nimue-rt/
Project-URL: Tracker, https://github.com/cogniteva/nimue-rt/issues
Platform: any
Classifier: Development Status :: 3 - Alpha
Classifier: Programming Language :: Python
License-File: LICENSE.txt
Requires-Dist: cython
Requires-Dist: wheel
Requires-Dist: rich >=10.16.1
Requires-Dist: pyyaml
Requires-Dist: h5py ==3.11.0
Requires-Dist: pluginlib ==0.9.0
Requires-Dist: python-dotenv ==0.20.0
Requires-Dist: semver ==3.0.2
Requires-Dist: psutil ==5.9.8
Requires-Dist: deepdiff ~=7.0
Requires-Dist: pandas ==2.2.2
Requires-Dist: importlib-metadata ; python_version < "3.8"
Provides-Extra: testing
Requires-Dist: setuptools ; extra == 'testing'
Requires-Dist: pytest ; extra == 'testing'
Requires-Dist: pytest-cov ; extra == 'testing'
